{
	"configurations" : 
	[
		{
			"directories" : 
			[
				{
					"build" : ".",
					"jsonFile" : "directory-.-Debug-f5ebdc15457944623624.json",
					"minimumCMakeVersion" : 
					{
						"string" : "3.23"
					},
					"projectIndex" : 0,
					"source" : ".",
					"targetIndexes" : 
					[
						0
					]
				}
			],
			"name" : "Debug",
			"projects" : 
			[
				{
					"directoryIndexes" : 
					[
						0
					],
					"name" : "beginner",
					"targetIndexes" : 
					[
						0
					]
				}
			],
			"targets" : 
			[
				{
					"directoryIndex" : 0,
					"id" : "beginner::@6890427a1f51a3e7e1df",
<<<<<<<< HEAD:cmake-build-debug/.cmake/api/v1/reply/codemodel-v2-90ccbc0369d1feab3f1a.json
					"jsonFile" : "target-beginner-Debug-1f98aa93fcd6d27956b7.json",
========
					"jsonFile" : "target-beginner-Debug-d054b3807c6d6044e3d2.json",
>>>>>>>> master:cmake-build-debug/.cmake/api/v1/reply/codemodel-v2-52279c4de6fce25ece6a.json
					"name" : "beginner",
					"projectIndex" : 0
				}
			]
		}
	],
	"kind" : "codemodel",
	"paths" : 
	{
		"build" : "/Users/hans/Desktop/code/cpp/alogrithm/algorithm/cmake-build-debug",
		"source" : "/Users/hans/Desktop/code/cpp/alogrithm/algorithm"
	},
	"version" : 
	{
		"major" : 2,
		"minor" : 4
	}
}
